{
	"class" : {
		"named:" : "hfm 1/31/2011 15:16" },
	"instance" : {
		"addProject:" : "hfm 11/29/2011 03:27",
		"createProject:" : "HernanMoralesDurand 8/23/2014 03:11",
		"currentProject" : "HernanMoralesDurand 8/23/2014 14:22",
		"currentProject:" : "HernanMoralesDurand 8/21/2014 15:18",
		"initializeWith:" : "hfm 10/5/2011 16:54",
		"lastProjects:" : "hfm 11/30/2011 03:15",
		"name" : "hfm 8/27/2010 15:21",
		"name:" : "hfm 4/9/2011 03:19",
		"preferences" : "hfm 9/3/2010 15:54",
		"printOn:" : "hfm 8/31/2010 17:40",
		"projectExists:" : "hfm 11/29/2011 02:55",
		"projectINamed:" : "hfm 11/29/2011 01:57",
		"projectNamed:" : "hfm 11/29/2011 01:57",
		"projectsBetween:and:" : "hfm 11/25/2010 01:48",
		"prvProjectExists:" : "hfm 11/25/2010 01:48",
		"removeProject:" : "hfm 11/25/2010 01:48",
		"renameProject:to:" : "hfm 8/31/2010 16:39",
		"userProjects" : "hfm 11/25/2010 01:48",
		"userProjects:" : "hfm 11/25/2010 01:49" } }
