{
	"class" : {
		"forDNA" : "hfm 10/5/2011 16:53",
		"forFrequency" : "hfm 10/5/2011 16:53",
		"forMicrosat" : "hfm 10/5/2011 16:53",
		"forRFLP" : "hfm 10/5/2011 16:53",
		"forStandard" : "hfm 10/5/2011 16:53" },
	"instance" : {
		"asString" : "HernanMoralesDurand 12/14/2013 14:42",
		"do:" : "HernanMoralesDurand 1/14/2014 19:32",
		"identifiers:" : "HernanMoralesDurand 4/8/2013 01:58",
		"sampleClass" : "hfm 3/16/2011 15:00",
		"sampleClass:" : "hfm 3/16/2011 15:00",
		"sequences" : "HernanMoralesDurand 4/8/2013 01:58",
		"sequences:" : "HernanMoralesDurand 1/14/2014 19:28",
		"writeSamplesOn:delimiter:" : "HernanMoralesDurand 12/14/2013 15:16" } }
